propulsion/__init__.py
propulsion/__main__.py
propulsion-0.1.0.post2.dist-info/LICENSE
propulsion-0.1.0.post2.dist-info/WHEEL
propulsion-0.1.0.post2.dist-info/METADATA
propulsion-0.1.0.post2.dist-info/RECORD
